apngtogif-0.1.0.dist-info/METADATA
apngtogif-0.1.0.dist-info/WHEEL
apngtogif.libs/libgcc_s-1e52349c.so.1
apngtogif/__init__.py
apngtogif/apngtogif.pypy310-pp73-x86_64-linux-gnu.so
apngtogif-0.1.0.dist-info/RECORD
