Metadata-Version: 2.4
Name: apngtogif
Version: 0.1.0
Classifier: Programming Language :: Rust
Classifier: Programming Language :: Python :: Implementation :: CPython
Classifier: Programming Language :: Python :: Implementation :: PyPy
Requires-Dist: maturin >=1.7.8
Summary: A Python package for converting APNG files to animated GIFs
Author-email: taskylizard <75871323+taskylizard@users.noreply.github.com>
Requires-Python: >=3.8
